{
  "publications": "出版物",
  "breadcrumbs": {
    "first": "出版物",
    "second": "{{breadcrumb}}",
    "third": "{{pubTitle}}"
  },
  "title": "{{pubTitle}}",
  "description": "{{pubDesc}}",
  "authorId": "{{authorId}}",
  "verified": "認証された制作者",
  "view_profile": "プロフィールを見る",
  "image": "イメージ",
  "video": "動画",
  "card": "カード",
  "collection": "コレクション",
  "pub_type": { "community": "コミュニティー", "editorial": "説明" },
  "comic_type": "漫画",
  "title_page": { "create": "出版物を作る", "edit": "出版物の編集" },
  "cancel": "取り消し",
  "embedded_collectibles": "出版物の他のコレクション",
  "form": {
    "cover": {
      "title": "サムネイルのアップロード",
      "description": "ファイル: PNG, JPG. 最大ファイルのサイズ: 30MB"
    },
    "teaser": {
      "title": "要約本",
      "placeholder": "読者から興味をそそるために短くて面白く作成してみましょう。"
    },
    "publish": "掲示"
  },
  "modal": {
    "add_video": {
      "label": "動画を追加する",
      "placeholder": "動画のURL",
      "description": "ユーチューブの動画リンクを入力してください。",
      "button": "動画を追加する"
    },
    "add_card": {
      "label": "出版物にNFTを追加する",
      "placeholder": "トークンのURL",
      "description": "https://paras.id/token/x.paras.near::1 トークンのリンクを入力してください。",
      "button": "NFTを追加する"
    },
    "add_collection": {
      "label": "出版物にコレクションを追加する",
      "placeholder": "コレクションのURL",
      "description": "コレクションのリンクを入力してください。 https://paras.id/collection/paradigm",
      "button": "コレクションを追加する"
    },
    "leaving_confirmation": {
      "label": "このページで出ますか？アップデートしない変更事項は保存できません。",
      "button_ok": "はい",
      "button_cancel": "いいえ"
    },
    "delete_publication": {
      "label": "あっ!",
      "description": "本当に{{publication}}の削除をしますか?",
      "button": "削除する"
    }
  },
  "error": {
    "maximum_cards": "最大{{num}}枚のカードを追加できます。",
    "maximum_collections": "最大{{num}}個のコレクションを追加できます。",
    "wrong_url": "正しいURLを入力してください。",
    "already_added_collection": "このコレクションはもう追加されました。",
    "maximum_file_size": "最大のファイルのサイズは{{num}}MBです。",
    "title_required": "タイトルを入力してください。",
    "cover_required": "サムネイルを追加してください。",
    "teaser_required": "要約本を入力してください。"
  },
  "delete": "削除",
  "text_editor": { "title": "タイトル", "placeholder": "内容を入力してください。。。" }
}
