{
	"tabs": {
		"overview": "Tổng quan",
		"attributes": "Thuộc tính",
		"owners": "Chủ sở hữu",
		"history": "Lịch sử",
		"description": "Mô tả",
		"token_info": "Thông tin token",
		"publications": "Ấn phẩm"
	},
	"banner_image": {
		"share": "Chia sẻ",
		"copy_link": "Sao chép đường dẫn",
		"play": "Play"
	},
	"top_info": {
		"three_dots": {
			"burn_nft": "Đốt NFT",
			"transfer_nft": "Chuyển NFT",
			"offer_nft": "Offer qua NFT",
			"see_token_series": "Xem token series",
			"report_card": "Báo xấu"
		},
		"sale_type": {
			"on_auction": "Đấu giá",
			"start_from": "Bắt đầu từ",
			"on_sale": "Đang giảm giá"
		},
		"bidding_price_type": {
			"high_bid": "Giá cao nhất",
			"start_bid": "Bắt đầu đặt thầu"
		},
		"bidding_list": {
			"auction_history": "Lịch sử đấu giá",
			"auction_ends_in_token": "Đấu giá kết thúc sau {{days}} ngày, {{hours}} {{mins}} {{secs}}s",
			"auction_ends_in_token_series": "Một số ấn bản đang được bán đấu giá",
			"summary_bid": "Tổng quan",
			"since": "Kể từ khi bắt đầu",
			"place_recent_bid": "Giá thầu gần đây",
			"bid": "Đấu thầu",
			"start_bid": "Bắt đầu đặt thầu",
			"place_bid": "Đặt giá thầu",
			"no_bid": "Không có nhà thầu tại thời điểm này"
		},
		"offer_list": {
			"active_offering": "Đang chào bán",
			"regular": "Thường xuyên",
			"trade_with_card": "Giao dịch với thẻ",
			"active_offers": "Đang chào bán",
			"no_offer": "Không có đề nghị tại thời điểm này",
			"highest_offer": "Đề nghị cao nhất",
			"offer_higher": "Đề nghị cao hơn",
			"lowest_offer": "Đề nghị thấp nhất",
			"all_offers": "Tất cả đang hoạt động",
			"send_offer": "Gửi lời đề nghị",
			"accept": "Chấp nhận",
			"delete": "Xóa bỏ",
			"no_trade": "Không có giao dịch tại thời điểm này",
			"highest": "Cao nhất",
			"volume": "Khối lượng",
			"by": "qua",
			"lowest": "Thấp nhất",
			"cancel": "Hủy bỏ"
		},
		"mint_nft": "mint NFT",
		"creator": "Nhà sáng tạo",
		"verified_creator": "Nhà sáng tạo đã được xác minh",
		"collection": "Bộ sưu tập",
		"top_collection": "Bộ sưu tập hàng đầu",
		"make_own_offer": "Đưa ra đề nghị của riêng bạn",
		"no_price": "Không có giá",
		"free": "Miễn phí"
	},
	"price_history": {
		"avg_price": "Giá trung bình",
		"no_price": "Không có giá tại thời điểm này",
		"all_time": "Tất cả thời gian",
		"1day": "1 ngày",
		"7days": "7 ngày",
		"1month": "1 tháng",
		"3months": "3 tháng",
		"6months": "6 tháng",
		"1year": "1 năm",
		"price": "Giá",
		"lowest_price": "Giá thấp nhất",
		"avg._price": "Trung bình Giá",
		"highest_price": "Giá cao nhất"
	},
	"dashed_info": {
		"own_by": "Sở hữu bởi",
		"owners": "Người sở hữu",
		"nft_edition_copies": "Phiên bản / Bản sao NFT",
		"tooltip_nft_edition_copies": "Số lượng bản sao của thẻ này",
		"rarity_score": "Điểm hiếm có",
		"rank": "Thứ hạng",
		"rarity_score_rank": "Xếp hạng / Điểm hiếm",
		"creator_royalty": "Tiền bản quyền của người sáng tạo",
		"tootlip_creator_royalty": "Tỷ lệ phần trăm từ mỗi lần bán hàng được phân bổ để hỗ trợ người sáng tạo."
	},
	"other_card": {
		"same_collection": "Cùng Bộ Sưu Tập",
		"see_collection": "Xem Bộ sưu tập",
		"other_creator": "Xem thêm từ nhà sáng tạo",
		"creators_profile": "Hồ sơ của nhà sáng tạo"
	},
	"attributes": {
		"attributes": "Thuộc tính",
		"rarity_score": "Điểm hiếm có",
		"rank": "Thứ hạng",
		"rank_rarity_score": "Xếp hạng {{rank}}, Điểm hiếm {{rarityScore}}",
		"no_attributes": "Không có thuộc tính",
		"rarity": "Độ hiếm"
	},
	"owners": {
		"sort_by": "Sắp xếp theo",
		"sort_lowest_price": "Giá thấp nhất",
		"sort_highest_price": "Giá cao nhất",
		"sort_lowest_edition": "Phiên bản thấp nhất",
		"sort_highest_edition": "Phiên bản cao nhất",
		"sort_az": "Tên người dùng AZ",
		"sort_za": "Tên người dùng ZA",
		"owners": "Chủ sở hữu",
		"no_owners": "Không có chủ sở hữu, trở thành người đầu tiên",
		"on_auction": "Đấu giá",
		"on_sale": "Đang giảm giá",
		"staked": "Staked",
		"not_for_sale": "Không phải để bán",
		"update": "Cập nhật",
		"buy": "Mua"
	},
	"histories": {
		"history": "Lịch sử",
		"no_history": "Không có tại thời điểm này",
		"put_on_auction": "Đem ra đấu giá",
		"add_bid_for": "Thêm giá thầu cho",
		"cancel_bid_from_auction": "Hủy đấu thầu từ cuộc đấu giá",
		"put_on_sale": "Đưa ra bán cho",
		"added_offer_nft_trade": "Thêm ưu đãi giao dịch NFT",
		"deleted_offer_nft_trade": "Đã xóa ưu đãi giao dịch NFT",
		"accept_nft_trade": "chấp nhận giao dịch NFT",
		"remove_from_sale": "Xóa khỏi mục bán",
		"staked_to": "Stake vào",
		"bought_from": "Mua từ",
		"for": "vì",
		"minted": "mint",
		"minted_by": "mint bởi",
		"burned": "đã đốt",
		"accept_offer": "đề nghị được chấp nhận từ",
		"with_auction_for": "với giá đấu cho",
		"transferred_to": "chuyển cho",
		"series_created_by": "Series được tạo bởi",
		"creator_put_series_not_sale": "Nhà sáng tạo không để bán",
		"creator_put_series_sale_for": "Nhà sáng tạo đã rao bán với giá",
		"creator_put_series_nonmintable": "Nhà sáng tạo đưa vào loại không thể mint được",
		"creator_decrease_series": "Nhà sáng tạo giảm các bản copy của sê-ri xuống",
		"add_offer_for": "Đã thêm offer cho",
		"removed_for": "Đã xóa offer"
	},
	"description": {
		"description": "Mô tả",
		"no_description": "Không có mô tả"
	},
	"token_info": {
		"token_info": "Thông tin",
		"smart_contract": "Hợp đồng thông minh",
		"image_link": "Đường dẫn tới hình ảnh",
		"locked_fee": "Phí khóa",
		"tooltip_locked_fee": "Đây là phí giao dịch bị khóa hiện tại. Mỗi lần cập nhật giá NFT cũng sẽ cập nhật giá trị theo phí giao dịch chung.",
		"token_id": "ID mã thông báo",
		"token_series_id": "ID token series"
	},
	"publications": {
		"publications": "Ấn phẩm",
		"no_publication": "Không có ấn phẩm tại thời điểm này"
	}
}
